{
  "description": "profile-aware validation rejects an event whose overnet_et is not defined by the selected profile contract",
  "input": {
    "contract_fixture": "fixtures/profile-contracts/valid-chat-message-contract.json",
    "event": {
      "id": "2121212121212121212121212121212121212121212121212121212121212121",
      "pubkey": "b4c5d6b4c5d6b4c5d6b4c5d6b4c5d6b4c5d6b4c5d6b4c5d6b4c5d6b4c5d6b4c5",
      "created_at": 1744300810,
      "kind": 7800,
      "tags": [
        ["overnet_v", "0.1.0"],
        ["overnet_et", "chat.message.unknown"],
        ["overnet_ot", "chat.channel"],
        ["overnet_oid", "channel:general"],
        ["v", "0.1.0"],
        ["t", "chat.message.unknown"],
        ["o", "chat.channel"],
        ["d", "channel:general"]
      ],
      "content": "{\"provenance\":{\"type\":\"native\"},\"body\":{\"text\":\"Hello\"}}",
      "sig": "babababababababababababababababababababababababababababababababababababababababababababababababababababababababababababababababa"
    }
  },
  "expected": {
    "overnet_valid": true,
    "profile_contract_valid": true,
    "profile_event_valid": false,
    "reason": "profile_event.event_type_undefined"
  }
}
